azure/__init__.py
azure/cli/__init__.py
azure/cli/command_modules/__init__.py
azure/cli/command_modules/container/__init__.py
azure/cli/command_modules/container/_client_factory.py
azure/cli/command_modules/container/_format.py
azure/cli/command_modules/container/_help.py
azure/cli/command_modules/container/_params.py
azure/cli/command_modules/container/_validators.py
azure/cli/command_modules/container/commands.py
azure/cli/command_modules/container/custom.py
azure_cli_container-0.3.18.dist-info/METADATA
azure_cli_container-0.3.18.dist-info/WHEEL
azure_cli_container-0.3.18.dist-info/top_level.txt
azure_cli_container-0.3.18.dist-info/RECORD
